tests/__init__.py
tests/test_tqdm_sound.py
tqdm_sound/__init__.py
tqdm_sound/_version.py
tqdm_sound/tqdm_sound.py
tqdm_sound/sounds/ryoji_ikeda/background_tone.wav
tqdm_sound/sounds/ryoji_ikeda/click_0.wav
tqdm_sound/sounds/ryoji_ikeda/click_1.wav
tqdm_sound/sounds/ryoji_ikeda/click_10.wav
tqdm_sound/sounds/ryoji_ikeda/click_11.wav
tqdm_sound/sounds/ryoji_ikeda/click_12.wav
tqdm_sound/sounds/ryoji_ikeda/click_13.wav
tqdm_sound/sounds/ryoji_ikeda/click_14.wav
tqdm_sound/sounds/ryoji_ikeda/click_15.wav
tqdm_sound/sounds/ryoji_ikeda/click_16.wav
tqdm_sound/sounds/ryoji_ikeda/click_17.wav
tqdm_sound/sounds/ryoji_ikeda/click_18.wav
tqdm_sound/sounds/ryoji_ikeda/click_19.wav
tqdm_sound/sounds/ryoji_ikeda/click_2.wav
tqdm_sound/sounds/ryoji_ikeda/click_20.wav
tqdm_sound/sounds/ryoji_ikeda/click_3.wav
tqdm_sound/sounds/ryoji_ikeda/click_4.wav
tqdm_sound/sounds/ryoji_ikeda/click_5.wav
tqdm_sound/sounds/ryoji_ikeda/click_6.wav
tqdm_sound/sounds/ryoji_ikeda/click_7.wav
tqdm_sound/sounds/ryoji_ikeda/click_8.wav
tqdm_sound/sounds/ryoji_ikeda/click_9.wav
tqdm_sound/sounds/ryoji_ikeda/end_tone.wav
tqdm_sound/sounds/ryoji_ikeda/mid_tone.wav
tqdm_sound/sounds/ryoji_ikeda/program_end_tone.wav
tqdm_sound/sounds/ryoji_ikeda/semi_major.wav
tqdm_sound/sounds/ryoji_ikeda/start_tone.wav
tqdm_sound-1.3.2.dist-info/licenses/LICENSE
tqdm_sound-1.3.2.dist-info/METADATA
tqdm_sound-1.3.2.dist-info/WHEEL
tqdm_sound-1.3.2.dist-info/top_level.txt
tqdm_sound-1.3.2.dist-info/RECORD
