Metadata-Version: 2.4
Name: tqdm_sound
Version: 1.3.2
Summary: Progress bars with sound enhancements
Home-page: https://github.com/looking-glass-station/tqdm_sound
Download-URL: https://github.com/looking-glass-station/tqdm_sound/v_1.3.2.tar.gz
Author: JH
Author-email: dev_gatehouse@proton.me
License: MIT
Keywords: tqdm,progress bar,progress alerts,progress soundsRyoji Ikeda
Classifier: Programming Language :: Python :: 3.9
Classifier: Programming Language :: Python :: 3.10
Classifier: Programming Language :: Python :: 3.11
Classifier: Programming Language :: Python :: 3.12
Classifier: License :: OSI Approved :: MIT License
Classifier: Operating System :: OS Independent
Requires-Python: >=3.9
License-File: LICENSE
Requires-Dist: build~=1.2.2.post1
Requires-Dist: cffi~=1.17.1
Requires-Dist: colorama~=0.4.6
Requires-Dist: iniconfig>=1.1.1
Requires-Dist: numpy>=1.26.0
Requires-Dist: packaging~=25.0
Requires-Dist: pluggy~=1.6.0
Requires-Dist: pycparser~=2.22
Requires-Dist: pynput~=1.8.1
Requires-Dist: pyproject_hooks~=1.2.0
Requires-Dist: pytest~=8.3.5
Requires-Dist: simpleaudio~=1.0.4
Requires-Dist: six~=1.17.0
Requires-Dist: sounddevice~=0.5.2
Requires-Dist: soundfile~=0.13.1
Requires-Dist: tqdm~=4.67.1
Dynamic: author
Dynamic: author-email
Dynamic: classifier
Dynamic: description
Dynamic: description-content-type
Dynamic: download-url
Dynamic: home-page
Dynamic: keywords
Dynamic: license
Dynamic: license-file
Dynamic: requires-dist
Dynamic: requires-python
Dynamic: summary
